LICENSE
MANIFEST.in
README.md
setup.cfg
setup.py
pythomics/__init__.py
pythomics.egg-info/PKG-INFO
pythomics.egg-info/SOURCES.txt
pythomics.egg-info/dependency_links.txt
pythomics.egg-info/not-zip-safe
pythomics.egg-info/requires.txt
pythomics.egg-info/top_level.txt
pythomics/genomics/__init__.py
pythomics/genomics/config.py
pythomics/genomics/parsers.py
pythomics/genomics/structures.py
pythomics/parsers/__init__.py
pythomics/parsers/config.py
pythomics/parsers/fasta.py
pythomics/parsers/fastq.py
pythomics/proteomics/__init__.py
pythomics/proteomics/config.py
pythomics/proteomics/digest.py
pythomics/proteomics/parsers.py
pythomics/proteomics/peptide.py
pythomics/proteomics/structures.py
pythomics/templates/__init__.py
pythomics/transcriptomics/__init__.py
pythomics/utils/__init__.py
scripts/fastadigest.py
scripts/fastadigeststats.py
scripts/fastxTrimmer.py
scripts/featureCollapser.py
scripts/fetchOrfs.py
scripts/incorporateGFF.py
scripts/incorporateVCF.py
scripts/intersectFiles.py
scripts/junctionalReads.py
scripts/proteinInference.py
scripts/ptmSummary.py