Metadata-Version: 2.1
Name: pythomics
Version: 0.4.1
Summary: A multi-omic python package
Home-page: https://github.com/chris7/pythomics
Author: Chris Mitchell
Author-email: chris.mit7@gmail.com
License: GPL3
Platform: UNKNOWN
Provides-Extra: all
